{
  "generatedAt": "2026-04-27T09:15:12.791Z",
  "lang": "ru",
  "batchId": "batch-09",
  "dataset": "2023-test1",
  "sourceWorkbenchDecisionsPath": "qbank-tools/generated/staging/ru-batch-09-workbench-decisions.json",
  "items": [
    {
      "qid": "q0721",
      "confirmedCorrectOptionKey": "B",
      "unknown": false,
      "reviewerNotes": ""
    },
    {
      "qid": "q0597",
      "confirmedCorrectOptionKey": "A",
      "unknown": false,
      "reviewerNotes": ""
    },
    {
      "qid": "q0891",
      "confirmedCorrectOptionKey": "B",
      "unknown": false,
      "reviewerNotes": ""
    },
    {
      "qid": "q0892",
      "confirmedCorrectOptionKey": "C",
      "unknown": false,
      "reviewerNotes": ""
    },
    {
      "qid": "q0734",
      "confirmedCorrectOptionKey": "D",
      "unknown": false,
      "reviewerNotes": ""
    },
    {
      "qid": "q0439",
      "confirmedCorrectOptionKey": "C",
      "unknown": false,
      "reviewerNotes": ""
    },
    {
      "qid": "q0514",
      "confirmedCorrectOptionKey": "B",
      "unknown": false,
      "reviewerNotes": ""
    },
    {
      "qid": "q0864",
      "confirmedCorrectOptionKey": "C",
      "unknown": false,
      "reviewerNotes": ""
    },
    {
      "qid": "q0880",
      "confirmedCorrectOptionKey": "D",
      "unknown": false,
      "reviewerNotes": ""
    },
    {
      "qid": "q0595",
      "confirmedCorrectOptionKey": "A",
      "unknown": false,
      "reviewerNotes": ""
    },
    {
      "qid": "q0829",
      "confirmedCorrectOptionKey": "B",
      "unknown": false,
      "reviewerNotes": ""
    },
    {
      "qid": "q0840",
      "confirmedCorrectOptionKey": "D",
      "unknown": false,
      "reviewerNotes": ""
    },
    {
      "qid": "q0112",
      "confirmedCorrectOptionKey": "D",
      "unknown": false,
      "reviewerNotes": ""
    },
    {
      "qid": "q0656",
      "confirmedCorrectOptionKey": "A",
      "unknown": false,
      "reviewerNotes": ""
    },
    {
      "qid": "q0479",
      "confirmedCorrectOptionKey": "C",
      "unknown": false,
      "reviewerNotes": ""
    },
    {
      "qid": "q0470",
      "confirmedCorrectOptionKey": "A",
      "unknown": false,
      "reviewerNotes": ""
    },
    {
      "qid": "q0836",
      "confirmedCorrectOptionKey": "A",
      "unknown": false,
      "reviewerNotes": ""
    },
    {
      "qid": "q0678",
      "confirmedCorrectOptionKey": "B",
      "unknown": false,
      "reviewerNotes": ""
    },
    {
      "qid": "q0781",
      "confirmedCorrectOptionKey": "D",
      "unknown": false,
      "reviewerNotes": ""
    },
    {
      "qid": "q0157",
      "confirmedCorrectOptionKey": "B",
      "unknown": false,
      "reviewerNotes": ""
    },
    {
      "qid": "q0841",
      "confirmedCorrectOptionKey": "A",
      "unknown": false,
      "reviewerNotes": ""
    },
    {
      "qid": "q0740",
      "confirmedCorrectOptionKey": "A",
      "unknown": false,
      "reviewerNotes": ""
    },
    {
      "qid": "q0718",
      "confirmedCorrectOptionKey": "D",
      "unknown": false,
      "reviewerNotes": ""
    },
    {
      "qid": "q0587",
      "confirmedCorrectOptionKey": "A",
      "unknown": false,
      "reviewerNotes": ""
    }
  ]
}
