{
  "generatedAt": "2026-04-09T03:12:36.022Z",
  "lang": "ja",
  "batchId": "batch-002",
  "dataset": "2023-test1",
  "qid": "q0695",
  "sourceMatchedPath": "imports/ja/batch-002/matched.json",
  "sourcePreviewPath": "qbank-tools/generated/staging/translations.ja.batch-002.full.preview.json",
  "sourceReportPath": "qbank-tools/generated/reports/full-batch-merge-review-ja-batch-002.json",
  "item": {
    "qid": "q0695",
    "sourceItemId": "screenshots/Screenshot 2026-04-07 at 17.50.02.png",
    "sourceImage": "screenshots/Screenshot 2026-04-07 at 17.50.02.png",
    "currentStagedLocaleCorrectOptionKey": "A",
    "confirmedCorrectOptionKey": "A",
    "unknown": false,
    "reviewerNotes": ""
  }
}
