{
  "generatedAt": "2026-04-13T09:23:56.151Z",
  "lang": "ja",
  "batchId": "batch-011",
  "dataset": "2023-test1",
  "sourceDecisionPath": "qbank-tools/generated/staging/ja-batch-011-unresolved-decisions.json",
  "items": [
    {
      "itemId": "screenshots/Screenshot 2026-04-07 at 18.18.34 1.png",
      "sourceSection": "auto-matched",
      "sourceImage": "screenshots/Screenshot 2026-04-07 at 18.18.34 1.png",
      "currentTopQid": "q0974",
      "currentTopScore": 84.928,
      "approvedQid": "q0453",
      "noneOfThese": false,
      "createNewQuestion": false,
      "unsure": false,
      "reviewerNotes": "",
      "status": "approved-existing-qid"
    },
    {
      "itemId": "screenshots/Screenshot 2026-04-07 at 18.18.47.png",
      "sourceSection": "auto-matched",
      "sourceImage": "screenshots/Screenshot 2026-04-07 at 18.18.47.png",
      "currentTopQid": "q0480",
      "currentTopScore": 73.132,
      "approvedQid": "q0505",
      "noneOfThese": false,
      "createNewQuestion": false,
      "unsure": false,
      "reviewerNotes": "",
      "status": "approved-existing-qid"
    },
    {
      "itemId": "screenshots/Screenshot 2026-04-07 at 18.18.26.png",
      "sourceSection": "review-needed",
      "sourceImage": "screenshots/Screenshot 2026-04-07 at 18.18.26.png",
      "currentTopQid": "q0830",
      "currentTopScore": 48.896,
      "approvedQid": "q0830",
      "noneOfThese": false,
      "createNewQuestion": false,
      "unsure": false,
      "reviewerNotes": "",
      "status": "approved-existing-qid"
    },
    {
      "itemId": "screenshots/Screenshot 2026-04-07 at 18.18.28.png",
      "sourceSection": "review-needed",
      "sourceImage": "screenshots/Screenshot 2026-04-07 at 18.18.28.png",
      "currentTopQid": "q0069",
      "currentTopScore": 66.924,
      "approvedQid": "q0069",
      "noneOfThese": false,
      "createNewQuestion": false,
      "unsure": false,
      "reviewerNotes": "",
      "status": "approved-existing-qid"
    },
    {
      "itemId": "screenshots/Screenshot 2026-04-07 at 18.18.29 1.png",
      "sourceSection": "review-needed",
      "sourceImage": "screenshots/Screenshot 2026-04-07 at 18.18.29 1.png",
      "currentTopQid": "q0174",
      "currentTopScore": 52.868,
      "approvedQid": "q0174",
      "noneOfThese": false,
      "createNewQuestion": false,
      "unsure": false,
      "reviewerNotes": "",
      "status": "approved-existing-qid"
    },
    {
      "itemId": "screenshots/Screenshot 2026-04-07 at 18.18.29.png",
      "sourceSection": "review-needed",
      "sourceImage": "screenshots/Screenshot 2026-04-07 at 18.18.29.png",
      "currentTopQid": "q0086",
      "currentTopScore": 47.491,
      "approvedQid": "q0262",
      "noneOfThese": false,
      "createNewQuestion": false,
      "unsure": false,
      "reviewerNotes": "",
      "status": "approved-existing-qid"
    },
    {
      "itemId": "screenshots/Screenshot 2026-04-07 at 18.18.30.png",
      "sourceSection": "review-needed",
      "sourceImage": "screenshots/Screenshot 2026-04-07 at 18.18.30.png",
      "currentTopQid": "q0745",
      "currentTopScore": 45.357,
      "approvedQid": "q0745",
      "noneOfThese": false,
      "createNewQuestion": false,
      "unsure": false,
      "reviewerNotes": "",
      "status": "approved-existing-qid"
    },
    {
      "itemId": "screenshots/Screenshot 2026-04-07 at 18.18.31.png",
      "sourceSection": "review-needed",
      "sourceImage": "screenshots/Screenshot 2026-04-07 at 18.18.31.png",
      "currentTopQid": "q0201",
      "currentTopScore": 61.411,
      "approvedQid": "q0201",
      "noneOfThese": false,
      "createNewQuestion": false,
      "unsure": false,
      "reviewerNotes": "",
      "status": "approved-existing-qid"
    },
    {
      "itemId": "screenshots/Screenshot 2026-04-07 at 18.18.32.png",
      "sourceSection": "review-needed",
      "sourceImage": "screenshots/Screenshot 2026-04-07 at 18.18.32.png",
      "currentTopQid": "q0511",
      "currentTopScore": 63.429,
      "approvedQid": "q0139",
      "noneOfThese": false,
      "createNewQuestion": false,
      "unsure": false,
      "reviewerNotes": "",
      "status": "approved-existing-qid"
    },
    {
      "itemId": "screenshots/Screenshot 2026-04-07 at 18.18.34.png",
      "sourceSection": "review-needed",
      "sourceImage": "screenshots/Screenshot 2026-04-07 at 18.18.34.png",
      "currentTopQid": "q0831",
      "currentTopScore": 48.305,
      "approvedQid": "q0831",
      "noneOfThese": false,
      "createNewQuestion": false,
      "unsure": false,
      "reviewerNotes": "",
      "status": "approved-existing-qid"
    },
    {
      "itemId": "screenshots/Screenshot 2026-04-07 at 18.18.35.png",
      "sourceSection": "review-needed",
      "sourceImage": "screenshots/Screenshot 2026-04-07 at 18.18.35.png",
      "currentTopQid": "q0121",
      "currentTopScore": 47.818,
      "approvedQid": "q0121",
      "noneOfThese": false,
      "createNewQuestion": false,
      "unsure": false,
      "reviewerNotes": "",
      "status": "approved-existing-qid"
    },
    {
      "itemId": "screenshots/Screenshot 2026-04-07 at 18.18.36.png",
      "sourceSection": "review-needed",
      "sourceImage": "screenshots/Screenshot 2026-04-07 at 18.18.36.png",
      "currentTopQid": "q0878",
      "currentTopScore": 70.242,
      "approvedQid": "q0755",
      "noneOfThese": false,
      "createNewQuestion": false,
      "unsure": false,
      "reviewerNotes": "",
      "status": "approved-existing-qid"
    },
    {
      "itemId": "screenshots/Screenshot 2026-04-07 at 18.18.38 1.png",
      "sourceSection": "review-needed",
      "sourceImage": "screenshots/Screenshot 2026-04-07 at 18.18.38 1.png",
      "currentTopQid": "q0837",
      "currentTopScore": 47.796,
      "approvedQid": "q0837",
      "noneOfThese": false,
      "createNewQuestion": false,
      "unsure": false,
      "reviewerNotes": "",
      "status": "approved-existing-qid"
    },
    {
      "itemId": "screenshots/Screenshot 2026-04-07 at 18.18.38.png",
      "sourceSection": "review-needed",
      "sourceImage": "screenshots/Screenshot 2026-04-07 at 18.18.38.png",
      "currentTopQid": "q0107",
      "currentTopScore": 54.752,
      "approvedQid": "q0107",
      "noneOfThese": false,
      "createNewQuestion": false,
      "unsure": false,
      "reviewerNotes": "",
      "status": "approved-existing-qid"
    },
    {
      "itemId": "screenshots/Screenshot 2026-04-07 at 18.18.39.png",
      "sourceSection": "review-needed",
      "sourceImage": "screenshots/Screenshot 2026-04-07 at 18.18.39.png",
      "currentTopQid": "q0619",
      "currentTopScore": 45.765,
      "approvedQid": "q0615",
      "noneOfThese": false,
      "createNewQuestion": false,
      "unsure": false,
      "reviewerNotes": "",
      "status": "approved-existing-qid"
    },
    {
      "itemId": "screenshots/Screenshot 2026-04-07 at 18.18.40 1.png",
      "sourceSection": "review-needed",
      "sourceImage": "screenshots/Screenshot 2026-04-07 at 18.18.40 1.png",
      "currentTopQid": "q0552",
      "currentTopScore": 61.751,
      "approvedQid": "q0569",
      "noneOfThese": false,
      "createNewQuestion": false,
      "unsure": false,
      "reviewerNotes": "",
      "status": "approved-existing-qid"
    },
    {
      "itemId": "screenshots/Screenshot 2026-04-07 at 18.18.40.png",
      "sourceSection": "review-needed",
      "sourceImage": "screenshots/Screenshot 2026-04-07 at 18.18.40.png",
      "currentTopQid": "q0707",
      "currentTopScore": 64.721,
      "approvedQid": "q0860",
      "noneOfThese": false,
      "createNewQuestion": false,
      "unsure": false,
      "reviewerNotes": "",
      "status": "approved-existing-qid"
    },
    {
      "itemId": "screenshots/Screenshot 2026-04-07 at 18.18.41.png",
      "sourceSection": "review-needed",
      "sourceImage": "screenshots/Screenshot 2026-04-07 at 18.18.41.png",
      "currentTopQid": "q0484",
      "currentTopScore": 50.711,
      "approvedQid": "q0484",
      "noneOfThese": false,
      "createNewQuestion": false,
      "unsure": false,
      "reviewerNotes": "",
      "status": "approved-existing-qid"
    },
    {
      "itemId": "screenshots/Screenshot 2026-04-07 at 18.18.42 1.png",
      "sourceSection": "review-needed",
      "sourceImage": "screenshots/Screenshot 2026-04-07 at 18.18.42 1.png",
      "currentTopQid": "q0655",
      "currentTopScore": 85.891,
      "approvedQid": "q0655",
      "noneOfThese": false,
      "createNewQuestion": false,
      "unsure": false,
      "reviewerNotes": "",
      "status": "approved-existing-qid"
    },
    {
      "itemId": "screenshots/Screenshot 2026-04-07 at 18.18.43.png",
      "sourceSection": "review-needed",
      "sourceImage": "screenshots/Screenshot 2026-04-07 at 18.18.43.png",
      "currentTopQid": "q0974",
      "currentTopScore": 55.513,
      "approvedQid": "q0465",
      "noneOfThese": false,
      "createNewQuestion": false,
      "unsure": false,
      "reviewerNotes": "",
      "status": "approved-existing-qid"
    },
    {
      "itemId": "screenshots/Screenshot 2026-04-07 at 18.18.44.png",
      "sourceSection": "review-needed",
      "sourceImage": "screenshots/Screenshot 2026-04-07 at 18.18.44.png",
      "currentTopQid": "q0613",
      "currentTopScore": 57.731,
      "approvedQid": "q0613",
      "noneOfThese": false,
      "createNewQuestion": false,
      "unsure": false,
      "reviewerNotes": "",
      "status": "approved-existing-qid"
    },
    {
      "itemId": "screenshots/Screenshot 2026-04-07 at 18.18.46.png",
      "sourceSection": "review-needed",
      "sourceImage": "screenshots/Screenshot 2026-04-07 at 18.18.46.png",
      "currentTopQid": "q0086",
      "currentTopScore": 66.911,
      "approvedQid": "q0067",
      "noneOfThese": false,
      "createNewQuestion": false,
      "unsure": false,
      "reviewerNotes": "",
      "status": "approved-existing-qid"
    },
    {
      "itemId": "screenshots/Screenshot 2026-04-07 at 18.18.48.png",
      "sourceSection": "review-needed",
      "sourceImage": "screenshots/Screenshot 2026-04-07 at 18.18.48.png",
      "currentTopQid": "q0167",
      "currentTopScore": 45.656,
      "approvedQid": "q0423",
      "noneOfThese": false,
      "createNewQuestion": false,
      "unsure": false,
      "reviewerNotes": "",
      "status": "approved-existing-qid"
    },
    {
      "itemId": "screenshots/Screenshot 2026-04-07 at 18.18.51.png",
      "sourceSection": "review-needed",
      "sourceImage": "screenshots/Screenshot 2026-04-07 at 18.18.51.png",
      "currentTopQid": "q0381",
      "currentTopScore": 59.683,
      "approvedQid": "q0381",
      "noneOfThese": false,
      "createNewQuestion": false,
      "unsure": false,
      "reviewerNotes": "",
      "status": "approved-existing-qid"
    },
    {
      "itemId": "screenshots/Screenshot 2026-04-07 at 18.18.53.png",
      "sourceSection": "review-needed",
      "sourceImage": "screenshots/Screenshot 2026-04-07 at 18.18.53.png",
      "currentTopQid": "q0491",
      "currentTopScore": 50.422,
      "approvedQid": "q0520",
      "noneOfThese": false,
      "createNewQuestion": false,
      "unsure": false,
      "reviewerNotes": "",
      "status": "approved-existing-qid"
    },
    {
      "itemId": "screenshots/Screenshot 2026-04-07 at 18.18.54 1.png",
      "sourceSection": "review-needed",
      "sourceImage": "screenshots/Screenshot 2026-04-07 at 18.18.54 1.png",
      "currentTopQid": "q0422",
      "currentTopScore": 47.518,
      "approvedQid": "q0422",
      "noneOfThese": false,
      "createNewQuestion": false,
      "unsure": false,
      "reviewerNotes": "",
      "status": "approved-existing-qid"
    },
    {
      "itemId": "screenshots/Screenshot 2026-04-07 at 18.18.54.png",
      "sourceSection": "review-needed",
      "sourceImage": "screenshots/Screenshot 2026-04-07 at 18.18.54.png",
      "currentTopQid": "q0496",
      "currentTopScore": 64.743,
      "approvedQid": "q0496",
      "noneOfThese": false,
      "createNewQuestion": false,
      "unsure": false,
      "reviewerNotes": "",
      "status": "approved-existing-qid"
    },
    {
      "itemId": "screenshots/Screenshot 2026-04-07 at 18.18.55.png",
      "sourceSection": "review-needed",
      "sourceImage": "screenshots/Screenshot 2026-04-07 at 18.18.55.png",
      "currentTopQid": "q0128",
      "currentTopScore": 57.864,
      "approvedQid": "q0128",
      "noneOfThese": false,
      "createNewQuestion": false,
      "unsure": false,
      "reviewerNotes": "",
      "status": "approved-existing-qid"
    },
    {
      "itemId": "screenshots/Screenshot 2026-04-07 at 18.18.56.png",
      "sourceSection": "review-needed",
      "sourceImage": "screenshots/Screenshot 2026-04-07 at 18.18.56.png",
      "currentTopQid": "q0769",
      "currentTopScore": 52.715,
      "approvedQid": "q0769",
      "noneOfThese": false,
      "createNewQuestion": false,
      "unsure": false,
      "reviewerNotes": "",
      "status": "approved-existing-qid"
    },
    {
      "itemId": "screenshots/Screenshot 2026-04-07 at 18.18.57.png",
      "sourceSection": "review-needed",
      "sourceImage": "screenshots/Screenshot 2026-04-07 at 18.18.57.png",
      "currentTopQid": "q0446",
      "currentTopScore": 54.895,
      "approvedQid": "q0446",
      "noneOfThese": false,
      "createNewQuestion": false,
      "unsure": false,
      "reviewerNotes": "",
      "status": "approved-existing-qid"
    },
    {
      "itemId": "screenshots/Screenshot 2026-04-07 at 18.18.58 1.png",
      "sourceSection": "review-needed",
      "sourceImage": "screenshots/Screenshot 2026-04-07 at 18.18.58 1.png",
      "currentTopQid": "q0817",
      "currentTopScore": 64.99,
      "approvedQid": "q0817",
      "noneOfThese": false,
      "createNewQuestion": false,
      "unsure": false,
      "reviewerNotes": "",
      "status": "approved-existing-qid"
    },
    {
      "itemId": "screenshots/Screenshot 2026-04-07 at 18.19.00 1.png",
      "sourceSection": "review-needed",
      "sourceImage": "screenshots/Screenshot 2026-04-07 at 18.19.00 1.png",
      "currentTopQid": "q0368",
      "currentTopScore": 52.022,
      "approvedQid": "q0468",
      "noneOfThese": false,
      "createNewQuestion": false,
      "unsure": false,
      "reviewerNotes": "",
      "status": "approved-existing-qid"
    },
    {
      "itemId": "screenshots/Screenshot 2026-04-07 at 18.19.01.png",
      "sourceSection": "review-needed",
      "sourceImage": "screenshots/Screenshot 2026-04-07 at 18.19.01.png",
      "currentTopQid": "q0761",
      "currentTopScore": 46.95,
      "approvedQid": "q0702",
      "noneOfThese": false,
      "createNewQuestion": false,
      "unsure": false,
      "reviewerNotes": "",
      "status": "approved-existing-qid"
    },
    {
      "itemId": "screenshots/Screenshot 2026-04-07 at 18.19.02.png",
      "sourceSection": "review-needed",
      "sourceImage": "screenshots/Screenshot 2026-04-07 at 18.19.02.png",
      "currentTopQid": "q0111",
      "currentTopScore": 53.608,
      "approvedQid": "q0111",
      "noneOfThese": false,
      "createNewQuestion": false,
      "unsure": false,
      "reviewerNotes": "",
      "status": "approved-existing-qid"
    }
  ]
}
