{
  "generatedAt": "2026-04-07T09:47:38.764Z",
  "lang": "ja",
  "batchId": "batch-001",
  "dataset": "2023-test1",
  "source": "imports/ja/batch-001/review-needed.json",
  "items": [
    {
      "itemId": "screenshots/1.png",
      "sourceImage": "screenshots/1.png",
      "currentTopQid": "q0761",
      "currentTopScore": 50.641,
      "decision": "unsure",
      "approvedQid": null,
      "notes": ""
    },
    {
      "itemId": "screenshots/Screenshot 2026-04-07 at 17.49.24.png",
      "sourceImage": "screenshots/Screenshot 2026-04-07 at 17.49.24.png",
      "currentTopQid": "q0871",
      "currentTopScore": 38.454,
      "decision": "unsure",
      "approvedQid": null,
      "notes": ""
    },
    {
      "itemId": "screenshots/Screenshot 2026-04-07 at 17.49.39.png",
      "sourceImage": "screenshots/Screenshot 2026-04-07 at 17.49.39.png",
      "currentTopQid": "q0820",
      "currentTopScore": 47.194,
      "decision": "unsure",
      "approvedQid": null,
      "notes": ""
    },
    {
      "itemId": "screenshots/Screenshot 2026-04-07 at 17.49.43.png",
      "sourceImage": "screenshots/Screenshot 2026-04-07 at 17.49.43.png",
      "currentTopQid": "q0319",
      "currentTopScore": 50.386,
      "decision": "unsure",
      "approvedQid": null,
      "notes": ""
    },
    {
      "itemId": "screenshots/Screenshot 2026-04-07 at 17.49.45.png",
      "sourceImage": "screenshots/Screenshot 2026-04-07 at 17.49.45.png",
      "currentTopQid": "q0780",
      "currentTopScore": 38.957,
      "decision": "unsure",
      "approvedQid": null,
      "notes": ""
    },
    {
      "itemId": "screenshots/Screenshot 2026-04-07 at 17.49.47 1.png",
      "sourceImage": "screenshots/Screenshot 2026-04-07 at 17.49.47 1.png",
      "currentTopQid": "q0483",
      "currentTopScore": 39.411,
      "decision": "unsure",
      "approvedQid": null,
      "notes": ""
    },
    {
      "itemId": "screenshots/Screenshot 2026-04-07 at 17.49.49 1.png",
      "sourceImage": "screenshots/Screenshot 2026-04-07 at 17.49.49 1.png",
      "currentTopQid": "q0054",
      "currentTopScore": 47.657,
      "decision": "unsure",
      "approvedQid": null,
      "notes": ""
    },
    {
      "itemId": "screenshots/Screenshot 2026-04-07 at 17.49.49.png",
      "sourceImage": "screenshots/Screenshot 2026-04-07 at 17.49.49.png",
      "currentTopQid": "q0895",
      "currentTopScore": 33.475,
      "decision": "unsure",
      "approvedQid": null,
      "notes": ""
    },
    {
      "itemId": "screenshots/Screenshot 2026-04-07 at 17.49.50.png",
      "sourceImage": "screenshots/Screenshot 2026-04-07 at 17.49.50.png",
      "currentTopQid": "q0073",
      "currentTopScore": 46.762,
      "decision": "unsure",
      "approvedQid": null,
      "notes": ""
    },
    {
      "itemId": "screenshots/Screenshot 2026-04-07 at 17.49.51.png",
      "sourceImage": "screenshots/Screenshot 2026-04-07 at 17.49.51.png",
      "currentTopQid": "q0126",
      "currentTopScore": 40.82,
      "decision": "unsure",
      "approvedQid": null,
      "notes": ""
    },
    {
      "itemId": "screenshots/Screenshot 2026-04-07 at 17.49.53 1.png",
      "sourceImage": "screenshots/Screenshot 2026-04-07 at 17.49.53 1.png",
      "currentTopQid": "q0591",
      "currentTopScore": 39.734,
      "decision": "unsure",
      "approvedQid": null,
      "notes": ""
    },
    {
      "itemId": "screenshots/Screenshot 2026-04-07 at 17.49.53.png",
      "sourceImage": "screenshots/Screenshot 2026-04-07 at 17.49.53.png",
      "currentTopQid": "q0333",
      "currentTopScore": 60.089,
      "decision": "unsure",
      "approvedQid": null,
      "notes": ""
    },
    {
      "itemId": "screenshots/Screenshot 2026-04-07 at 17.49.54.png",
      "sourceImage": "screenshots/Screenshot 2026-04-07 at 17.49.54.png",
      "currentTopQid": "q0110",
      "currentTopScore": 36.894,
      "decision": "unsure",
      "approvedQid": null,
      "notes": ""
    },
    {
      "itemId": "screenshots/Screenshot 2026-04-07 at 17.49.55.png",
      "sourceImage": "screenshots/Screenshot 2026-04-07 at 17.49.55.png",
      "currentTopQid": "q0237",
      "currentTopScore": 54.838,
      "decision": "unsure",
      "approvedQid": null,
      "notes": ""
    },
    {
      "itemId": "screenshots/Screenshot 2026-04-07 at 17.49.56.png",
      "sourceImage": "screenshots/Screenshot 2026-04-07 at 17.49.56.png",
      "currentTopQid": "q0680",
      "currentTopScore": 43.215,
      "decision": "unsure",
      "approvedQid": null,
      "notes": ""
    },
    {
      "itemId": "screenshots/Screenshot 2026-04-07 at 17.49.57.png",
      "sourceImage": "screenshots/Screenshot 2026-04-07 at 17.49.57.png",
      "currentTopQid": "q0466",
      "currentTopScore": 55.124,
      "decision": "unsure",
      "approvedQid": null,
      "notes": ""
    },
    {
      "itemId": "screenshots/Screenshot 2026-04-07 at 17.49.58.png",
      "sourceImage": "screenshots/Screenshot 2026-04-07 at 17.49.58.png",
      "currentTopQid": "q0033",
      "currentTopScore": 50.72,
      "decision": "unsure",
      "approvedQid": null,
      "notes": ""
    },
    {
      "itemId": "screenshots/Screenshot 2026-04-07 at 17.49.59.png",
      "sourceImage": "screenshots/Screenshot 2026-04-07 at 17.49.59.png",
      "currentTopQid": "q0664",
      "currentTopScore": 42.068,
      "decision": "unsure",
      "approvedQid": null,
      "notes": ""
    },
    {
      "itemId": "screenshots/Screenshot 2026-04-07 at 17.50.00.png",
      "sourceImage": "screenshots/Screenshot 2026-04-07 at 17.50.00.png",
      "currentTopQid": "q0617",
      "currentTopScore": 45.063,
      "decision": "unsure",
      "approvedQid": null,
      "notes": ""
    }
  ]
}
